{
  "version": "2.0.0",
  "categories": [
    {
      "id": 1,
      "name_key": "category_greetings",
      "icon": "handshake"
    },
    {
      "id": 2,
      "name_key": "category_daily",
      "icon": "sun"
    },
    {
      "id": 3,
      "name_key": "category_business",
      "icon": "briefcase"
    },
    {
      "id": 4,
      "name_key": "category_travel",
      "icon": "airplane"
    },
    {
      "id": 5,
      "name_key": "category_shopping",
      "icon": "shopping_cart"
    }
  ],
  "lessons": [
    {
      "id": 1,
      "sentence": "Hello!",
      "category_id": 1,
      "difficulty": 1,
      "translations": {
        "en": "Hello!",
        "ko": "안녕하세요!",
        "ja": "こんにちは！",
        "zh-CN": "你好！",
        "zh-TW": "你好！",
        "es": "¡Hola!",
        "fr": "Bonjour !",
        "de": "Hallo!",
        "it": "Ciao!",
        "pt": "Olá!",
        "ru": "Привет!",
        "ar": "مرحبا!",
        "hi": "नमस्ते!",
        "th": "สวัสดี!",
        "vi": "Xin chào!"
      }
    },
    {
      "id": 2,
      "sentence": "Thank you.",
      "category_id": 1,
      "difficulty": 1,
      "translations": {
        "en": "Thank you.",
        "ko": "감사합니다.",
        "ja": "ありがとうございます。",
        "zh-CN": "谢谢。",
        "zh-TW": "謝謝。",
        "es": "Gracias.",
        "fr": "Merci.",
        "de": "Danke.",
        "it": "Grazie.",
        "pt": "Obrigado.",
        "ru": "Спасибо.",
        "ar": "شكرا.",
        "hi": "धन्यवाद।",
        "th": "ขอบคุณ",
        "vi": "Cảm ơn."
      }
    },
    {
      "id": 3,
      "sentence": "Nice to meet you.",
      "category_id": 1,
      "difficulty": 1,
      "translations": {
        "en": "Nice to meet you.",
        "ko": "만나서 반갑습니다.",
        "ja": "はじめまして。",
        "zh-CN": "很高兴认识你。",
        "zh-TW": "很高興認識你。",
        "es": "Encantado de conocerte.",
        "fr": "Enchanté(e).",
        "de": "Freut mich, Sie kennenzulernen.",
        "it": "Piacere di conoscerti.",
        "pt": "Prazer em conhecê-lo.",
        "ru": "Приятно познакомиться.",
        "ar": "سررت بلقائك.",
        "hi": "आपसे मिलकर खुशी हुई।",
        "th": "ยินดีที่ได้รู้จัก",
        "vi": "Rất vui được gặp bạn."
      }
    },
    {
      "id": 4,
      "sentence": "How are you?",
      "category_id": 1,
      "difficulty": 1,
      "translations": {
        "en": "How are you?",
        "ko": "잘 지내세요?",
        "ja": "お元気ですか？",
        "zh-CN": "你好吗？",
        "zh-TW": "你好嗎？",
        "es": "¿Cómo estás?",
        "fr": "Comment allez-vous ?",
        "de": "Wie geht es Ihnen?",
        "it": "Come stai?",
        "pt": "Como você está?",
        "ru": "Как дела?",
        "ar": "كيف حالك؟",
        "hi": "आप कैसे हैं?",
        "th": "คุณเป็นอย่างไรบ้าง?",
        "vi": "Bạn khỏe không?"
      }
    },
    {
      "id": 5,
      "sentence": "I'm fine, thank you.",
      "category_id": 1,
      "difficulty": 1,
      "translations": {
        "en": "I'm fine, thank you.",
        "ko": "잘 지내요, 감사합니다.",
        "ja": "元気です、ありがとうございます。",
        "zh-CN": "我很好，谢谢。",
        "zh-TW": "我很好，謝謝。",
        "es": "Estoy bien, gracias.",
        "fr": "Je vais bien, merci.",
        "de": "Mir geht es gut, danke.",
        "it": "Sto bene, grazie.",
        "pt": "Estou bem, obrigado.",
        "ru": "Я в порядке, спасибо.",
        "ar": "أنا بخير، شكرا.",
        "hi": "मैं ठीक हूँ, धन्यवाद।",
        "th": "ฉันสบายดี ขอบคุณ",
        "vi": "Tôi khỏe, cảm ơn."
      }
    },
    {
      "id": 6,
      "sentence": "What's your name?",
      "category_id": 1,
      "difficulty": 1,
      "translations": {
        "en": "What's your name?",
        "ko": "이름이 뭐예요?",
        "ja": "お名前は何ですか？",
        "zh-CN": "你叫什么名字？",
        "zh-TW": "你叫什麼名字？",
        "es": "¿Cómo te llamas?",
        "fr": "Comment vous appelez-vous ?",
        "de": "Wie heißen Sie?",
        "it": "Come ti chiami?",
        "pt": "Qual é o seu nome?",
        "ru": "Как вас зовут?",
        "ar": "ما اسمك؟",
        "hi": "आपका नाम क्या है?",
        "th": "คุณชื่ออะไร?",
        "vi": "Bạn tên là gì?"
      }
    },
    {
      "id": 7,
      "sentence": "My name is John.",
      "category_id": 1,
      "difficulty": 1,
      "translations": {
        "en": "My name is John.",
        "ko": "제 이름은 John입니다.",
        "ja": "私の名前はジョンです。",
        "zh-CN": "我叫约翰。",
        "zh-TW": "我叫約翰。",
        "es": "Me llamo John.",
        "fr": "Je m'appelle John.",
        "de": "Mein Name ist John.",
        "it": "Mi chiamo John.",
        "pt": "Meu nome é John.",
        "ru": "Меня зовут Джон.",
        "ar": "اسمي جون.",
        "hi": "मेरा नाम जॉन है।",
        "th": "ผมชื่อจอห์น",
        "vi": "Tên tôi là John."
      }
    },
    {
      "id": 8,
      "sentence": "Nice to meet you too.",
      "category_id": 1,
      "difficulty": 1,
      "translations": {
        "en": "Nice to meet you too.",
        "ko": "저도 만나서 반갑습니다.",
        "ja": "こちらこそ、よろしくお願いします。",
        "zh-CN": "我也很高兴认识你。",
        "zh-TW": "我也很高興認識你。",
        "es": "Encantado de conocerte también.",
        "fr": "Moi aussi, enchanté(e).",
        "de": "Freut mich auch.",
        "it": "Piacere mio.",
        "pt": "Prazer em conhecê-lo também.",
        "ru": "Мне тоже приятно познакомиться.",
        "ar": "سررت بلقائك أيضا.",
        "hi": "मुझे भी आपसे मिलकर खुशी हुई।",
        "th": "ยินดีที่ได้รู้จักเช่นกัน",
        "vi": "Tôi cũng rất vui được gặp bạn."
      }
    },
    {
      "id": 9,
      "sentence": "See you later.",
      "category_id": 1,
      "difficulty": 1,
      "translations": {
        "en": "See you later.",
        "ko": "나중에 봐요.",
        "ja": "また後で。",
        "zh-CN": "回头见。",
        "zh-TW": "回頭見。",
        "es": "Hasta luego.",
        "fr": "À plus tard.",
        "de": "Bis später.",
        "it": "A dopo.",
        "pt": "Até logo.",
        "ru": "Увидимся позже.",
        "ar": "أراك لاحقا.",
        "hi": "बाद में मिलते हैं।",
        "th": "แล้วเจอกัน",
        "vi": "Hẹn gặp lại."
      }
    },
    {
      "id": 10,
      "sentence": "Have a nice day!",
      "category_id": 1,
      "difficulty": 1,
      "translations": {
        "en": "Have a nice day!",
        "ko": "좋은 하루 보내세요!",
        "ja": "良い一日を！",
        "zh-CN": "祝你有美好的一天！",
        "zh-TW": "祝你有美好的一天！",
        "es": "¡Que tengas un buen día!",
        "fr": "Bonne journée !",
        "de": "Einen schönen Tag noch!",
        "it": "Buona giornata!",
        "pt": "Tenha um bom dia!",
        "ru": "Хорошего дня!",
        "ar": "أتمنى لك يوما سعيدا!",
        "hi": "आपका दिन शुभ हो!",
        "th": "ขอให้เป็นวันที่ดี!",
        "vi": "Chúc bạn một ngày tốt lành!"
      }
    },
    {
      "id": 11,
      "sentence": "Excuse me.",
      "category_id": 2,
      "difficulty": 1,
      "translations": {
        "en": "Excuse me.",
        "ko": "실례합니다.",
        "ja": "すみません。",
        "zh-CN": "打扰一下。",
        "zh-TW": "打擾一下。",
        "es": "Disculpe.",
        "fr": "Excusez-moi.",
        "de": "Entschuldigung.",
        "it": "Mi scusi.",
        "pt": "Com licença.",
        "ru": "Извините.",
        "ar": "عذرا.",
        "hi": "माफ़ कीजिए।",
        "th": "ขอโทษครับ/ค่ะ",
        "vi": "Xin lỗi."
      }
    },
    {
      "id": 12,
      "sentence": "I'm sorry.",
      "category_id": 2,
      "difficulty": 1,
      "translations": {
        "en": "I'm sorry.",
        "ko": "죄송합니다.",
        "ja": "申し訳ありません。",
        "zh-CN": "对不起。",
        "zh-TW": "對不起。",
        "es": "Lo siento.",
        "fr": "Je suis désolé(e).",
        "de": "Es tut mir leid.",
        "it": "Mi dispiace.",
        "pt": "Desculpe.",
        "ru": "Мне жаль.",
        "ar": "أنا آسف.",
        "hi": "मुझे खेद है।",
        "th": "ผม/ฉันขอโทษ",
        "vi": "Tôi xin lỗi."
      }
    },
    {
      "id": 13,
      "sentence": "No problem.",
      "category_id": 2,
      "difficulty": 1,
      "translations": {
        "en": "No problem.",
        "ko": "괜찮아요.",
        "ja": "大丈夫です。",
        "zh-CN": "没问题。",
        "zh-TW": "沒問題。",
        "es": "No hay problema.",
        "fr": "Pas de problème.",
        "de": "Kein Problem.",
        "it": "Nessun problema.",
        "pt": "Sem problema.",
        "ru": "Без проблем.",
        "ar": "لا مشكلة.",
        "hi": "कोई बात नहीं।",
        "th": "ไม่เป็นไร",
        "vi": "Không sao."
      }
    },
    {
      "id": 14,
      "sentence": "What time is it?",
      "category_id": 2,
      "difficulty": 1,
      "translations": {
        "en": "What time is it?",
        "ko": "지금 몇 시예요?",
        "ja": "今何時ですか？",
        "zh-CN": "现在几点了？",
        "zh-TW": "現在幾點了？",
        "es": "¿Qué hora es?",
        "fr": "Quelle heure est-il ?",
        "de": "Wie spät ist es?",
        "it": "Che ore sono?",
        "pt": "Que horas são?",
        "ru": "Который час?",
        "ar": "كم الساعة؟",
        "hi": "कितने बजे हैं?",
        "th": "ตอนนี้กี่โมง?",
        "vi": "Mấy giờ rồi?"
      }
    },
    {
      "id": 15,
      "sentence": "Where is the restroom?",
      "category_id": 2,
      "difficulty": 1,
      "translations": {
        "en": "Where is the restroom?",
        "ko": "화장실이 어디예요?",
        "ja": "トイレはどこですか？",
        "zh-CN": "洗手间在哪里？",
        "zh-TW": "洗手間在哪裡？",
        "es": "¿Dónde está el baño?",
        "fr": "Où sont les toilettes ?",
        "de": "Wo ist die Toilette?",
        "it": "Dov'è il bagno?",
        "pt": "Onde fica o banheiro?",
        "ru": "Где туалет?",
        "ar": "أين الحمام؟",
        "hi": "शौचालय कहाँ है?",
        "th": "ห้องน้ำอยู่ที่ไหน?",
        "vi": "Nhà vệ sinh ở đâu?"
      }
    },
    {
      "id": 16,
      "sentence": "Can you help me?",
      "category_id": 2,
      "difficulty": 1,
      "translations": {
        "en": "Can you help me?",
        "ko": "도와주실 수 있나요?",
        "ja": "手伝っていただけますか？",
        "zh-CN": "你能帮我吗？",
        "zh-TW": "你能幫我嗎？",
        "es": "¿Puede ayudarme?",
        "fr": "Pouvez-vous m'aider ?",
        "de": "Können Sie mir helfen?",
        "it": "Può aiutarmi?",
        "pt": "Você pode me ajudar?",
        "ru": "Вы можете мне помочь?",
        "ar": "هل يمكنك مساعدتي؟",
        "hi": "क्या आप मेरी मदद कर सकते हैं?",
        "th": "คุณช่วยฉันได้ไหม?",
        "vi": "Bạn có thể giúp tôi không?"
      }
    },
    {
      "id": 17,
      "sentence": "I don't understand.",
      "category_id": 2,
      "difficulty": 1,
      "translations": {
        "en": "I don't understand.",
        "ko": "이해하지 못했어요.",
        "ja": "わかりません。",
        "zh-CN": "我不明白。",
        "zh-TW": "我不明白。",
        "es": "No entiendo.",
        "fr": "Je ne comprends pas.",
        "de": "Ich verstehe nicht.",
        "it": "Non capisco.",
        "pt": "Eu não entendo.",
        "ru": "Я не понимаю.",
        "ar": "لا أفهم.",
        "hi": "मुझे समझ नहीं आया।",
        "th": "ฉันไม่เข้าใจ",
        "vi": "Tôi không hiểu."
      }
    },
    {
      "id": 18,
      "sentence": "Could you repeat that?",
      "category_id": 2,
      "difficulty": 2,
      "translations": {
        "en": "Could you repeat that?",
        "ko": "다시 말씀해 주시겠어요?",
        "ja": "もう一度言っていただけますか？",
        "zh-CN": "你能再说一遍吗？",
        "zh-TW": "你能再說一遍嗎？",
        "es": "¿Podría repetir eso?",
        "fr": "Pourriez-vous répéter ?",
        "de": "Könnten Sie das wiederholen?",
        "it": "Potrebbe ripetere?",
        "pt": "Você poderia repetir?",
        "ru": "Не могли бы вы повторить?",
        "ar": "هل يمكنك تكرار ذلك؟",
        "hi": "क्या आप दोहरा सकते हैं?",
        "th": "คุณช่วยพูดอีกครั้งได้ไหม?",
        "vi": "Bạn có thể nhắc lại không?"
      }
    },
    {
      "id": 19,
      "sentence": "Could you speak more slowly?",
      "category_id": 2,
      "difficulty": 2,
      "translations": {
        "en": "Could you speak more slowly?",
        "ko": "좀 더 천천히 말씀해 주시겠어요?",
        "ja": "もう少しゆっくり話していただけますか？",
        "zh-CN": "你能说慢一点吗？",
        "zh-TW": "你能說慢一點嗎？",
        "es": "¿Podría hablar más despacio?",
        "fr": "Pourriez-vous parler plus lentement ?",
        "de": "Könnten Sie langsamer sprechen?",
        "it": "Potrebbe parlare più lentamente?",
        "pt": "Você poderia falar mais devagar?",
        "ru": "Не могли бы вы говорить медленнее?",
        "ar": "هل يمكنك التحدث ببطء أكثر؟",
        "hi": "क्या आप धीरे बोल सकते हैं?",
        "th": "คุณช่วยพูดช้าลงได้ไหม?",
        "vi": "Bạn có thể nói chậm hơn không?"
      }
    },
    {
      "id": 20,
      "sentence": "What does this mean?",
      "category_id": 2,
      "difficulty": 1,
      "translations": {
        "en": "What does this mean?",
        "ko": "이게 무슨 뜻이에요?",
        "ja": "これはどういう意味ですか？",
        "zh-CN": "这是什么意思？",
        "zh-TW": "這是什麼意思？",
        "es": "¿Qué significa esto?",
        "fr": "Qu'est-ce que cela signifie ?",
        "de": "Was bedeutet das?",
        "it": "Cosa significa questo?",
        "pt": "O que isso significa?",
        "ru": "Что это значит?",
        "ar": "ماذا يعني هذا؟",
        "hi": "इसका क्या मतलब है?",
        "th": "นี่หมายความว่าอะไร?",
        "vi": "Điều này có nghĩa là gì?"
      }
    },
    {
      "id": 21,
      "sentence": "How much is this?",
      "category_id": 5,
      "difficulty": 1,
      "translations": {
        "en": "How much is this?",
        "ko": "이거 얼마예요?",
        "ja": "これはいくらですか？",
        "zh-CN": "这个多少钱？",
        "zh-TW": "這個多少錢？",
        "es": "¿Cuánto cuesta esto?",
        "fr": "Combien ça coûte ?",
        "de": "Wie viel kostet das?",
        "it": "Quanto costa questo?",
        "pt": "Quanto custa isso?",
        "ru": "Сколько это стоит?",
        "ar": "كم سعر هذا؟",
        "hi": "यह कितने का है?",
        "th": "อันนี้เท่าไหร่?",
        "vi": "Cái này bao nhiêu tiền?"
      }
    },
    {
      "id": 22,
      "sentence": "Can I try this on?",
      "category_id": 5,
      "difficulty": 1,
      "translations": {
        "en": "Can I try this on?",
        "ko": "이거 입어봐도 될까요?",
        "ja": "試着してもいいですか？",
        "zh-CN": "我可以试穿吗？",
        "zh-TW": "我可以試穿嗎？",
        "es": "¿Puedo probarme esto?",
        "fr": "Puis-je l'essayer ?",
        "de": "Kann ich das anprobieren?",
        "it": "Posso provarlo?",
        "pt": "Posso experimentar?",
        "ru": "Можно примерить?",
        "ar": "هل يمكنني تجربة هذا؟",
        "hi": "क्या मैं इसे पहनकर देख सकता हूँ?",
        "th": "ฉันลองได้ไหม?",
        "vi": "Tôi có thể thử cái này không?"
      }
    },
    {
      "id": 23,
      "sentence": "I'll take this one.",
      "category_id": 5,
      "difficulty": 1,
      "translations": {
        "en": "I'll take this one.",
        "ko": "이걸로 할게요.",
        "ja": "これにします。",
        "zh-CN": "我要这个。",
        "zh-TW": "我要這個。",
        "es": "Me llevo este.",
        "fr": "Je prends celui-ci.",
        "de": "Ich nehme das hier.",
        "it": "Prendo questo.",
        "pt": "Vou levar este.",
        "ru": "Я возьму это.",
        "ar": "سآخذ هذا.",
        "hi": "मैं यह लूँगा।",
        "th": "ฉันจะเอาอันนี้",
        "vi": "Tôi sẽ lấy cái này."
      }
    },
    {
      "id": 24,
      "sentence": "Do you have this in a different size?",
      "category_id": 5,
      "difficulty": 2,
      "translations": {
        "en": "Do you have this in a different size?",
        "ko": "이거 다른 사이즈 있나요?",
        "ja": "別のサイズはありますか？",
        "zh-CN": "这个有别的尺码吗？",
        "zh-TW": "這個有別的尺碼嗎？",
        "es": "¿Tiene esto en otra talla?",
        "fr": "Avez-vous une autre taille ?",
        "de": "Haben Sie das in einer anderen Größe?",
        "it": "Avete una taglia diversa?",
        "pt": "Tem outro tamanho?",
        "ru": "У вас есть другой размер?",
        "ar": "هل لديك مقاس آخر؟",
        "hi": "क्या यह दूसरे साइज़ में है?",
        "th": "มีไซส์อื่นไหม?",
        "vi": "Bạn có size khác không?"
      }
    },
    {
      "id": 25,
      "sentence": "Can I pay by card?",
      "category_id": 5,
      "difficulty": 1,
      "translations": {
        "en": "Can I pay by card?",
        "ko": "카드로 결제할 수 있나요?",
        "ja": "カードで支払えますか？",
        "zh-CN": "可以刷卡吗？",
        "zh-TW": "可以刷卡嗎？",
        "es": "¿Puedo pagar con tarjeta?",
        "fr": "Puis-je payer par carte ?",
        "de": "Kann ich mit Karte bezahlen?",
        "it": "Posso pagare con carta?",
        "pt": "Posso pagar com cartão?",
        "ru": "Можно оплатить картой?",
        "ar": "هل يمكنني الدفع بالبطاقة؟",
        "hi": "क्या मैं कार्ड से भुगतान कर सकता हूँ?",
        "th": "จ่ายบัตรได้ไหม?",
        "vi": "Tôi có thể thanh toán bằng thẻ không?"
      }
    },
    {
      "id": 26,
      "sentence": "I'd like to return this.",
      "category_id": 5,
      "difficulty": 2,
      "translations": {
        "en": "I'd like to return this.",
        "ko": "이거 반품하고 싶어요.",
        "ja": "これを返品したいのですが。",
        "zh-CN": "我想退货。",
        "zh-TW": "我想退貨。",
        "es": "Me gustaría devolver esto.",
        "fr": "Je voudrais retourner ceci.",
        "de": "Ich möchte das zurückgeben.",
        "it": "Vorrei restituire questo.",
        "pt": "Gostaria de devolver isso.",
        "ru": "Я хотел бы вернуть это.",
        "ar": "أريد إرجاع هذا.",
        "hi": "मैं इसे वापस करना चाहता हूँ।",
        "th": "ฉันอยากคืนสินค้านี้",
        "vi": "Tôi muốn trả lại cái này."
      }
    },
    {
      "id": 27,
      "sentence": "Could I have the check, please?",
      "category_id": 4,
      "difficulty": 1,
      "translations": {
        "en": "Could I have the check, please?",
        "ko": "계산서 주시겠어요?",
        "ja": "お会計お願いします。",
        "zh-CN": "请结账。",
        "zh-TW": "請結帳。",
        "es": "¿Me trae la cuenta, por favor?",
        "fr": "L'addition, s'il vous plaît.",
        "de": "Die Rechnung, bitte.",
        "it": "Il conto, per favore.",
        "pt": "A conta, por favor.",
        "ru": "Счёт, пожалуйста.",
        "ar": "الحساب من فضلك.",
        "hi": "बिल दीजिए।",
        "th": "ขอบิลด้วยครับ/ค่ะ",
        "vi": "Cho tôi hóa đơn."
      }
    },
    {
      "id": 28,
      "sentence": "I have a reservation.",
      "category_id": 4,
      "difficulty": 1,
      "translations": {
        "en": "I have a reservation.",
        "ko": "예약했어요.",
        "ja": "予約しています。",
        "zh-CN": "我有预约。",
        "zh-TW": "我有預約。",
        "es": "Tengo una reserva.",
        "fr": "J'ai une réservation.",
        "de": "Ich habe eine Reservierung.",
        "it": "Ho una prenotazione.",
        "pt": "Eu tenho uma reserva.",
        "ru": "У меня есть бронь.",
        "ar": "لدي حجز.",
        "hi": "मेरा आरक्षण है।",
        "th": "ฉันจองไว้แล้ว",
        "vi": "Tôi có đặt chỗ."
      }
    },
    {
      "id": 29,
      "sentence": "Where is the nearest subway station?",
      "category_id": 4,
      "difficulty": 2,
      "translations": {
        "en": "Where is the nearest subway station?",
        "ko": "가장 가까운 지하철역이 어디예요?",
        "ja": "一番近い地下鉄の駅はどこですか？",
        "zh-CN": "最近的地铁站在哪里？",
        "zh-TW": "最近的地鐵站在哪裡？",
        "es": "¿Dónde está la estación de metro más cercana?",
        "fr": "Où est la station de métro la plus proche ?",
        "de": "Wo ist die nächste U-Bahn-Station?",
        "it": "Dov'è la stazione della metro più vicina?",
        "pt": "Onde fica a estação de metrô mais próxima?",
        "ru": "Где ближайшая станция метро?",
        "ar": "أين أقرب محطة مترو؟",
        "hi": "निकटतम मेट्रो स्टेशन कहाँ है?",
        "th": "สถานีรถไฟใต้ดินที่ใกล้ที่สุดอยู่ที่ไหน?",
        "vi": "Ga tàu điện ngầm gần nhất ở đâu?"
      }
    },
    {
      "id": 30,
      "sentence": "How do I get to the airport?",
      "category_id": 4,
      "difficulty": 2,
      "translations": {
        "en": "How do I get to the airport?",
        "ko": "공항에 어떻게 가나요?",
        "ja": "空港へはどうやって行けばいいですか？",
        "zh-CN": "去机场怎么走？",
        "zh-TW": "去機場怎麼走？",
        "es": "¿Cómo llego al aeropuerto?",
        "fr": "Comment aller à l'aéroport ?",
        "de": "Wie komme ich zum Flughafen?",
        "it": "Come arrivo all'aeroporto?",
        "pt": "Como chego ao aeroporto?",
        "ru": "Как добраться до аэропорта?",
        "ar": "كيف أصل إلى المطار؟",
        "hi": "एयरपोर्ट कैसे जाऊं?",
        "th": "ไปสนามบินยังไง?",
        "vi": "Làm sao để đến sân bay?"
      }
    },
    {
      "id": 31,
      "sentence": "Is this seat taken?",
      "category_id": 4,
      "difficulty": 1,
      "translations": {
        "en": "Is this seat taken?",
        "ko": "이 자리 있나요?",
        "ja": "この席は空いていますか？",
        "zh-CN": "这个座位有人吗？",
        "zh-TW": "這個座位有人嗎？",
        "es": "¿Está ocupado este asiento?",
        "fr": "Ce siège est-il pris ?",
        "de": "Ist dieser Platz frei?",
        "it": "Questo posto è occupato?",
        "pt": "Este assento está ocupado?",
        "ru": "Это место занято?",
        "ar": "هل هذا المقعد محجوز؟",
        "hi": "क्या यह सीट खाली है?",
        "th": "ที่นั่งนี้ว่างไหม?",
        "vi": "Chỗ này có ai ngồi không?"
      }
    },
    {
      "id": 32,
      "sentence": "Can I have a menu, please?",
      "category_id": 4,
      "difficulty": 1,
      "translations": {
        "en": "Can I have a menu, please?",
        "ko": "메뉴판 주시겠어요?",
        "ja": "メニューをいただけますか？",
        "zh-CN": "请给我菜单。",
        "zh-TW": "請給我菜單。",
        "es": "¿Puedo ver el menú, por favor?",
        "fr": "Puis-je avoir le menu, s'il vous plaît ?",
        "de": "Kann ich bitte die Speisekarte haben?",
        "it": "Posso avere il menù, per favore?",
        "pt": "Posso ver o cardápio, por favor?",
        "ru": "Можно меню, пожалуйста?",
        "ar": "هل يمكنني الحصول على القائمة؟",
        "hi": "मेन्यू दीजिए।",
        "th": "ขอเมนูด้วยครับ/ค่ะ",
        "vi": "Cho tôi xem thực đơn."
      }
    },
    {
      "id": 33,
      "sentence": "I'd like to order.",
      "category_id": 4,
      "difficulty": 1,
      "translations": {
        "en": "I'd like to order.",
        "ko": "주문하고 싶어요.",
        "ja": "注文したいのですが。",
        "zh-CN": "我想点餐。",
        "zh-TW": "我想點餐。",
        "es": "Me gustaría pedir.",
        "fr": "Je voudrais commander.",
        "de": "Ich möchte bestellen.",
        "it": "Vorrei ordinare.",
        "pt": "Gostaria de fazer o pedido.",
        "ru": "Я хотел бы заказать.",
        "ar": "أريد أن أطلب.",
        "hi": "मैं ऑर्डर करना चाहता हूँ।",
        "th": "ฉันอยากสั่งอาหาร",
        "vi": "Tôi muốn gọi món."
      }
    },
    {
      "id": 34,
      "sentence": "Could I have some water, please?",
      "category_id": 4,
      "difficulty": 1,
      "translations": {
        "en": "Could I have some water, please?",
        "ko": "물 좀 주시겠어요?",
        "ja": "お水をいただけますか？",
        "zh-CN": "请给我一杯水。",
        "zh-TW": "請給我一杯水。",
        "es": "¿Podría darme agua, por favor?",
        "fr": "Puis-je avoir de l'eau, s'il vous plaît ?",
        "de": "Könnte ich etwas Wasser haben, bitte?",
        "it": "Potrei avere dell'acqua, per favore?",
        "pt": "Poderia me dar água, por favor?",
        "ru": "Можно воды, пожалуйста?",
        "ar": "هل يمكنني الحصول على ماء؟",
        "hi": "पानी दीजिए।",
        "th": "ขอน้ำด้วยครับ/ค่ะ",
        "vi": "Cho tôi xin nước."
      }
    },
    {
      "id": 35,
      "sentence": "Nice to meet you. I'm the new employee.",
      "category_id": 3,
      "difficulty": 2,
      "translations": {
        "en": "Nice to meet you. I'm the new employee.",
        "ko": "만나서 반갑습니다. 신입사원입니다.",
        "ja": "はじめまして。新入社員です。",
        "zh-CN": "很高兴认识你。我是新员工。",
        "zh-TW": "很高興認識你。我是新員工。",
        "es": "Encantado. Soy el nuevo empleado.",
        "fr": "Enchanté. Je suis le nouveau employé.",
        "de": "Freut mich. Ich bin der neue Mitarbeiter.",
        "it": "Piacere. Sono il nuovo dipendente.",
        "pt": "Prazer. Sou o novo funcionário.",
        "ru": "Приятно познакомиться. Я новый сотрудник.",
        "ar": "سررت بلقائك. أنا الموظف الجديد.",
        "hi": "आपसे मिलकर खुशी हुई। मैं नया कर्मचारी हूँ।",
        "th": "ยินดีที่ได้รู้จัก ผมเป็นพนักงานใหม่",
        "vi": "Rất vui được gặp. Tôi là nhân viên mới."
      }
    },
    {
      "id": 36,
      "sentence": "I have a meeting at 10.",
      "category_id": 3,
      "difficulty": 1,
      "translations": {
        "en": "I have a meeting at 10.",
        "ko": "10시에 회의가 있어요.",
        "ja": "10時に会議があります。",
        "zh-CN": "我10点有个会议。",
        "zh-TW": "我10點有個會議。",
        "es": "Tengo una reunión a las 10.",
        "fr": "J'ai une réunion à 10 heures.",
        "de": "Ich habe um 10 Uhr ein Meeting.",
        "it": "Ho una riunione alle 10.",
        "pt": "Tenho uma reunião às 10.",
        "ru": "У меня встреча в 10.",
        "ar": "لدي اجتماع الساعة 10.",
        "hi": "10 बजे मेरी मीटिंग है।",
        "th": "ฉันมีประชุมตอน 10 โมง",
        "vi": "Tôi có cuộc họp lúc 10 giờ."
      }
    },
    {
      "id": 37,
      "sentence": "Could you send me the file?",
      "category_id": 3,
      "difficulty": 2,
      "translations": {
        "en": "Could you send me the file?",
        "ko": "파일 보내주시겠어요?",
        "ja": "ファイルを送っていただけますか？",
        "zh-CN": "你能把文件发给我吗？",
        "zh-TW": "你能把文件發給我嗎？",
        "es": "¿Podría enviarme el archivo?",
        "fr": "Pourriez-vous m'envoyer le fichier ?",
        "de": "Könnten Sie mir die Datei schicken?",
        "it": "Potrebbe inviarmi il file?",
        "pt": "Você poderia me enviar o arquivo?",
        "ru": "Не могли бы вы отправить мне файл?",
        "ar": "هل يمكنك إرسال الملف لي؟",
        "hi": "क्या आप मुझे फ़ाइल भेज सकते हैं?",
        "th": "คุณช่วยส่งไฟล์ให้ฉันได้ไหม?",
        "vi": "Bạn có thể gửi file cho tôi không?"
      }
    },
    {
      "id": 38,
      "sentence": "I'll get back to you soon.",
      "category_id": 3,
      "difficulty": 2,
      "translations": {
        "en": "I'll get back to you soon.",
        "ko": "곧 연락드릴게요.",
        "ja": "すぐにご連絡します。",
        "zh-CN": "我会尽快回复你。",
        "zh-TW": "我會盡快回覆你。",
        "es": "Le responderé pronto.",
        "fr": "Je vous recontacterai bientôt.",
        "de": "Ich melde mich bald bei Ihnen.",
        "it": "La ricontatterò presto.",
        "pt": "Entrarei em contato em breve.",
        "ru": "Я скоро свяжусь с вами.",
        "ar": "سأرد عليك قريبا.",
        "hi": "मैं जल्द ही संपर्क करूँगा।",
        "th": "ฉันจะติดต่อกลับเร็วๆ นี้",
        "vi": "Tôi sẽ liên hệ lại sớm."
      }
    },
    {
      "id": 39,
      "sentence": "Let me check my schedule.",
      "category_id": 3,
      "difficulty": 2,
      "translations": {
        "en": "Let me check my schedule.",
        "ko": "제 일정을 확인해볼게요.",
        "ja": "スケジュールを確認させてください。",
        "zh-CN": "让我查一下我的日程。",
        "zh-TW": "讓我查一下我的日程。",
        "es": "Déjeme revisar mi agenda.",
        "fr": "Laissez-moi vérifier mon emploi du temps.",
        "de": "Lassen Sie mich meinen Terminplan überprüfen.",
        "it": "Mi faccia controllare la mia agenda.",
        "pt": "Deixe-me verificar minha agenda.",
        "ru": "Позвольте проверить мое расписание.",
        "ar": "دعني أتحقق من جدولي.",
        "hi": "मुझे अपना शेड्यूल देखने दीजिए।",
        "th": "ให้ฉันเช็คตารางก่อน",
        "vi": "Để tôi kiểm tra lịch."
      }
    },
    {
      "id": 40,
      "sentence": "Thank you for your time.",
      "category_id": 3,
      "difficulty": 1,
      "translations": {
        "en": "Thank you for your time.",
        "ko": "시간 내주셔서 감사합니다.",
        "ja": "お時間をいただきありがとうございます。",
        "zh-CN": "感谢您抽出时间。",
        "zh-TW": "感謝您抽出時間。",
        "es": "Gracias por su tiempo.",
        "fr": "Merci pour votre temps.",
        "de": "Vielen Dank für Ihre Zeit.",
        "it": "Grazie per il suo tempo.",
        "pt": "Obrigado pelo seu tempo.",
        "ru": "Спасибо за ваше время.",
        "ar": "شكرا لوقتك.",
        "hi": "आपके समय के लिए धन्यवाद।",
        "th": "ขอบคุณสำหรับเวลาของคุณ",
        "vi": "Cảm ơn bạn đã dành thời gian."
      }
    }
  ]
}
